gym_poly_reactor/__init__.py
gym_poly_reactor/envs/__init__.py
gym_poly_reactor/envs/get_do_mpc_model.py
gym_poly_reactor/envs/params.py
gym_poly_reactor/envs/poly_reactor.py
gym_poly_reactor-0.2.dist-info/LICENSE
gym_poly_reactor-0.2.dist-info/METADATA
gym_poly_reactor-0.2.dist-info/WHEEL
gym_poly_reactor-0.2.dist-info/top_level.txt
gym_poly_reactor-0.2.dist-info/RECORD
